pl_cpu/registerFile.v
`timescale 1 ns / 1 ps

module registerFile #(
    parameter data_width = 32,
    parameter address_width = 5
)(clk, rst_n, we, w_addr, w_data, r_addr1, r_data1, r_addr2, r_data2);

    input wire clk;
    input wire rst_n;
    input wire we;
    input wire [address_width -1 :0] w_addr;
    input wire [data_width -1 :0] w_data;
    input wire [address_width -1 :0] r_addr1;
    input wire [address_width -1 :0] r_addr2;

    output wire [data_width-1 :0] r_data1;
    output wire [data_width-1 :0] r_data2;

    localparam n_regs = 2 ** (address_width);

    reg [data_width-1:0] registers [0:n_regs-1];

    integer i;

    always @(posedge clk or negedge rst_n)
    begin 
        if (!rst_n)
        begin 
            for (i = 0; i < n_regs; i=i+1)
            begin 
                registers[i] <= {data_width{1'b0}};
            end
        end
        else 
            if (we && (w_addr != 0))
            begin 
                registers[w_addr] <= w_data;
            end
    end

    assign r_data1 = (r_addr1 == 0) ? {data_width{1'b0}} : registers[r_addr1];
    assign r_data2 = (r_addr2 == 0) ? {data_width{1'b0}} : registers[r_addr2];

endmodule

instruction_decoder/instruction_decoder.v
`timescale 1 ns / 1 ps

module instruction_decoder (
    input wire [31:0] instr,
    output wire [6:0] opcode,
    output wire [4:0] rd,
    output wire [2:0] funct3,
    output wire [4:0] rs1,
    output wire [4:0] rs2,
    output wire [6:0] funct7,

    output reg [31:0] imm_out

);

    assign opcode = instr[6:0];
    assign rd = instr[11:7];
    assign funct3 = instr[14:12];
    assign rs1 = instr[19:15];
    assign rs2 = instr[24:20];
    assign funct7 = instr[31:25];

    always @(*)
    begin 
        case(opcode) 
            //I type
            7'b0010011,  //immediate arithmetic and logical ops
            7'b0000011, //memory loads
            7'b1100111, //jalr
            7'b1110011: //env or sys
            imm_out =  {{20{instr[31]}}, instr[31:20]}; //sign-extended

            // S type
            7'b0100011:
            imm_out = {{20{instr[31]}}, instr[31:25], instr[11:7]};

            //B type
            7'b1100011:
            imm_out = {{19{instr[31]}}, instr[31], instr[7], instr[30:25], instr[11:8], 1'b0};

            //U type
            7'b0110111, //lui
            7'b0010111: //auipc
            imm_out = {instr[31:12], {12{1'b0}}};

            //J type
            7'b1101111:
            imm_out = {{11{instr[31]}} , instr[31], instr[19:12], instr[20], instr[30:21], 1'b0};

            default: imm_out = 32'b0;

        endcase
    end

endmodule

single_cpu/instruction_decode.v
`timescale 1 ns / 1 ps

module instruction_decode (
    input wire clk,
    input wire rst_n,
    input [31:0] instr,

    input  wire        we,
    input  wire [4:0]  w_addr,
    input  wire [31:0] w_data,

    output wire [6:0] opcode,
    output wire [4:0] rd,
    output wire [2:0] funct3,
    output wire [4:0] rs1,
    output wire [4:0] rs2,
    output wire [6:0] funct7,

    output wire [31:0] imm_out,
    output wire [31:0] rs1_data,
    output wire [31:0] rs2_data
);

instruction_decoder ID_stage (
    .instr(instr),
    .opcode(opcode),
    .rd(rd),
    .funct3(funct3),
    .rs1(rs1),
    .rs2(rs2),
    .funct7(funct7),

    .imm_out(imm_out)

);

registerFile #(
    .data_width(32),
    .address_width(5)
) RegFile (.clk(clk), .rst_n(rst_n), .we(we), .w_addr(w_addr), .w_data(w_data), .r_addr1(rs1), .r_data1(rs1_data), 
    .r_addr2(rs2), .r_data2(rs2_data));

    
endmodule

instruction_decode/instruction_decode_tb.v
`timescale 1 ns / 1 ps

module instruction_decode_tb;

    reg clk;
    reg rst_n;
    reg [31:0] instr;

    reg we;
    reg [4:0]  w_addr;
    reg [31:0] w_data;

    wire [6:0] opcode;
    wire [4:0] rd;
    wire [2:0] funct3;
    wire [4:0] rs1;
    wire [4:0] rs2;
    wire [6:0] funct7;

    wire [31:0] imm_out;
    wire [31:0] rs1_data;
    wire [31:0] rs2_data;

    instruction_decode DUT (
    .clk(clk),
    .rst_n(rst_n),
    .instr(instr),

    .we(we),
    .w_addr(w_addr),
    .w_data(w_data),

    .opcode(opcode),
    .rd(rd),
    .funct3(funct3),
    .rs1(rs1),
    .rs2(rs2),
    .funct7(funct7),

    .imm_out(imm_out),
    .rs1_data(rs1_data),
    .rs2_data(rs2_data)
);

    always #5 clk = ~clk;

    initial
    begin 

        $dumpfile("instr_decode_wave.vcd");
        $dumpvars(0, instruction_decode_tb);

        clk = 0;
        rst_n = 0;
        instr = 32'b0;

        we     = 0;
        w_addr = 0;
        w_data = 0;

        #12;
        rst_n = 1;

        // Write x1 = 10
        @(negedge clk);
        we     = 1;
        w_addr = 5'd1;
        w_data = 32'd10;

        // Write x2 = 20
        @(negedge clk);
        w_addr = 5'd2;
        w_data = 32'd20;

        // Write x4 = 40
        @(negedge clk);
        w_addr = 5'd4;
        w_data = 32'd40;

        
        @(negedge clk);
        we = 0;

        $display("REGISTER CHECK: x1=%d | x2=%d | x4=%d",
         DUT.RegFile.registers[1],
         DUT.RegFile.registers[2],
         DUT.RegFile.registers[4]);

        // 1. I-Type: addi x1, x0, 2
        instr = 32'h00200093;
        #10;

        $display("opcode=%h | rd=%d | rs1=%d | imm=%h | rs1_data=%d | rs2_data=%d", opcode, rd, rs1, imm_out, rs1_data, rs2_data);


        // 2. I-Type: addi x2, x0, 3
        instr = 32'h00300113;
        #10;

       $display("opcode=%h | rd=%d | rs1=%d | imm=%h | rs1_data=%d | rs2_data=%d", opcode, rd, rs1, imm_out, rs1_data, rs2_data);


        // 3. R-Type: add x3, x1, x2
        instr = 32'h002081B3;
        #10;

        $display("opcode=%h | rd=%d | rs1=%d | rs2=%d | funct3=%h | funct7=%h | rs1_data=%d | rs2_data=%d", opcode, rd, rs1, rs2, funct3, funct7, rs1_data, rs2_data);


        // 4. S-Type: sw x3, 8(x4)
        instr = 32'h00322423;
        #10;

        $display("opcode=%h | rs1=%d | rs2=%d | imm=%h | rs1_data=%d | rs2_data=%d", opcode, rs1, rs2, imm_out, rs1_data, rs2_data);


        // 5. B-Type: beq x1, x2, -8
        instr = 32'hFE208CE3;
        #10;

        $display("opcode=%h | rs1=%d | rs2=%d | imm=%h | rs1_data=%d | rs2_data=%d", opcode, rs1, rs2, imm_out, rs1_data, rs2_data);


        // 6. U-Type: lui x5, 0x12345
        instr = 32'h123452B7;
        #10;

        $display("opcode=%h | rd=%d | imm=%h", opcode, rd, imm_out);


        // 7. J-Type: jal x1, -16
        instr = 32'hFF1FF0EF;
        #10;

        $display("opcode=%h | rd=%d | imm=%h", opcode, rd, imm_out);


        $display("Test complete");
        $finish;


    end

endmodule

instruction_decode/instr_decode_wave.vcd
$version Generated by VerilatedVcd $end
$timescale 1ps $end
 $scope module $rootio $end
 $upscope $end
 $scope module instruction_decode_tb $end
  $var wire 1 O clk $end
  $var wire 1 # rst_n $end
  $var wire 32 $ instr [31:0] $end
  $var wire 1 % we $end
  $var wire 5 & w_addr [4:0] $end
  $var wire 32 ' w_data [31:0] $end
  $var wire 7 ( opcode [6:0] $end
  $var wire 5 ) rd [4:0] $end
  $var wire 3 * funct3 [2:0] $end
  $var wire 5 + rs1 [4:0] $end
  $var wire 5 , rs2 [4:0] $end
  $var wire 7 - funct7 [6:0] $end
  $var wire 32 P imm_out [31:0] $end
  $var wire 32 Q rs1_data [31:0] $end
  $var wire 32 R rs2_data [31:0] $end
  $scope module DUT $end
   $var wire 1 O clk $end
   $var wire 1 # rst_n $end
   $var wire 32 $ instr [31:0] $end
   $var wire 1 % we $end
   $var wire 5 & w_addr [4:0] $end
   $var wire 32 ' w_data [31:0] $end
   $var wire 7 ( opcode [6:0] $end
   $var wire 5 ) rd [4:0] $end
   $var wire 3 * funct3 [2:0] $end
   $var wire 5 + rs1 [4:0] $end
   $var wire 5 , rs2 [4:0] $end
   $var wire 7 - funct7 [6:0] $end
   $var wire 32 P imm_out [31:0] $end
   $var wire 32 Q rs1_data [31:0] $end
   $var wire 32 R rs2_data [31:0] $end
   $scope module ID_stage $end
    $var wire 32 $ instr [31:0] $end
    $var wire 7 ( opcode [6:0] $end
    $var wire 5 ) rd [4:0] $end
    $var wire 3 * funct3 [2:0] $end
    $var wire 5 + rs1 [4:0] $end
    $var wire 5 , rs2 [4:0] $end
    $var wire 7 - funct7 [6:0] $end
    $var wire 32 P imm_out [31:0] $end
   $upscope $end
   $scope module RegFile $end
    $var wire 32 S data_width [31:0] $end
    $var wire 32 T address_width [31:0] $end
    $var wire 1 O clk $end
    $var wire 1 # rst_n $end
    $var wire 1 % we $end
    $var wire 5 & w_addr [4:0] $end
    $var wire 32 ' w_data [31:0] $end
    $var wire 5 + r_addr1 [4:0] $end
    $var wire 5 , r_addr2 [4:0] $end
    $var wire 32 Q r_data1 [31:0] $end
    $var wire 32 R r_data2 [31:0] $end
    $var wire 32 S n_regs [31:0] $end
    $var wire 32 . registers[0] [31:0] $end
    $var wire 32 / registers[1] [31:0] $end
    $var wire 32 0 registers[2] [31:0] $end
    $var wire 32 1 registers[3] [31:0] $end
    $var wire 32 2 registers[4] [31:0] $end
    $var wire 32 3 registers[5] [31:0] $end
    $var wire 32 4 registers[6] [31:0] $end
    $var wire 32 5 registers[7] [31:0] $end
    $var wire 32 6 registers[8] [31:0] $end
    $var wire 32 7 registers[9] [31:0] $end
    $var wire 32 8 registers[10] [31:0] $end
    $var wire 32 9 registers[11] [31:0] $end
    $var wire 32 : registers[12] [31:0] $end
    $var wire 32 ; registers[13] [31:0] $end
    $var wire 32 < registers[14] [31:0] $end
    $var wire 32 = registers[15] [31:0] $end
    $var wire 32 > registers[16] [31:0] $end
    $var wire 32 ? registers[17] [31:0] $end
    $var wire 32 @ registers[18] [31:0] $end
    $var wire 32 A registers[19] [31:0] $end
    $var wire 32 B registers[20] [31:0] $end
    $var wire 32 C registers[21] [31:0] $end
    $var wire 32 D registers[22] [31:0] $end
    $var wire 32 E registers[23] [31:0] $end
    $var wire 32 F registers[24] [31:0] $end
    $var wire 32 G registers[25] [31:0] $end
    $var wire 32 H registers[26] [31:0] $end
    $var wire 32 I registers[27] [31:0] $end
    $var wire 32 J registers[28] [31:0] $end
    $var wire 32 K registers[29] [31:0] $end
    $var wire 32 L registers[30] [31:0] $end
    $var wire 32 M registers[31] [31:0] $end
    $var wire 32 N i [31:0] $end
   $upscope $end
  $upscope $end
 $upscope $end
$enddefinitions $end


#0
0#
b00000000000000000000000000000000 $
0%
b00000 &
b00000000000000000000000000000000 '
b0000000 (
b00000 )
b000 *
b00000 +
b00000 ,
b0000000 -
b00000000000000000000000000000000 .
b00000000000000000000000000000000 /
b00000000000000000000000000000000 0
b00000000000000000000000000000000 1
b00000000000000000000000000000000 2
b00000000000000000000000000000000 3
b00000000000000000000000000000000 4
b00000000000000000000000000000000 5
b00000000000000000000000000000000 6
b00000000000000000000000000000000 7
b00000000000000000000000000000000 8
b00000000000000000000000000000000 9
b00000000000000000000000000000000 :
b00000000000000000000000000000000 ;
b00000000000000000000000000000000 <
b00000000000000000000000000000000 =
b00000000000000000000000000000000 >
b00000000000000000000000000000000 ?
b00000000000000000000000000000000 @
b00000000000000000000000000000000 A
b00000000000000000000000000000000 B
b00000000000000000000000000000000 C
b00000000000000000000000000000000 D
b00000000000000000000000000000000 E
b00000000000000000000000000000000 F
b00000000000000000000000000000000 G
b00000000000000000000000000000000 H
b00000000000000000000000000000000 I
b00000000000000000000000000000000 J
b00000000000000000000000000000000 K
b00000000000000000000000000000000 L
b00000000000000000000000000000000 M
b00000000000000000000000000000000 N
0O
b00000000000000000000000000000000 P
b00000000000000000000000000000000 Q
b00000000000000000000000000000000 R
b00000000000000000000000000100000 S
b00000000000000000000000000000101 T
#5000
b00000000000000000000000000100000 N
1O
#10000
0O
#12000
1#
#15000
1O
#20000
1%
b00001 &
b00000000000000000000000000001010 '
0O
#25000
b00000000000000000000000000001010 /
1O
#30000
b00010 &
b00000000000000000000000000010100 '
0O
#35000
b00000000000000000000000000010100 0
1O
#40000
b00100 &
b00000000000000000000000000101000 '
0O
#45000
b00000000000000000000000000101000 2
1O
#50000
b00000000001000000000000010010011 $
0%
b0010011 (
b00001 )
b00010 ,
0O
b00000000000000000000000000000010 P
b00000000000000000000000000010100 R
#55000
1O
#60000
b00000000001100000000000100010011 $
b00010 )
b00011 ,
0O
b00000000000000000000000000000011 P
b00000000000000000000000000000000 R
#65000
1O
#70000
b00000000001000001000000110110011 $
b0110011 (
b00011 )
b00001 +
b00010 ,
0O
b00000000000000000000000000000000 P
b00000000000000000000000000001010 Q
b00000000000000000000000000010100 R
#75000
1O
#80000
b00000000001100100010010000100011 $
b0100011 (
b01000 )
b010 *
b00100 +
b00011 ,
0O
b00000000000000000000000000001000 P
b00000000000000000000000000101000 Q
b00000000000000000000000000000000 R
#85000
1O
#90000
b11111110001000001000110011100011 $
b1100011 (
b11001 )
b000 *
b00001 +
b00010 ,
b1111111 -
0O
b11111111111111111111111111111000 P
b00000000000000000000000000001010 Q
b00000000000000000000000000010100 R
#95000
1O
#100000
b00010010001101000101001010110111 $
b0110111 (
b00101 )
b101 *
b01000 +
b00011 ,
b0001001 -
0O
b00010010001101000101000000000000 P
b00000000000000000000000000000000 Q
b00000000000000000000000000000000 R
#105000
1O
#110000
b11111111000111111111000011101111 $
b1101111 (
b00001 )
b111 *
b11111 +
b10001 ,
b1111111 -
0O
b11111111111111111111111111110000 P
