dec_gray2b/dec_gray2b.v
`timescale 1 ns / 1ps

module dec_gray2b #(
    parameter bit_width = 4
)(dec_out, dec_in);

    input wire [bit_width -1:0] dec_in;
    output reg [bit_width -1:0] dec_out;

    integer i;

    always @(*)
    begin
     
     dec_out[bit_width -1] = dec_in[bit_width -1];

     for (i = bit_width - 2; i >= 0 ; i = i - 1)
     begin
        dec_out[i] = dec_out[i+1] ^ dec_in[i];
     end
 

    end

endmodule

dec_gray2b/dec_gray2b_tb.v
`timescale 1 ns / 1 ps

module dec_gray2b_tb;

    parameter bit_Width = 4;

    reg [bit_Width -1 : 0] dec_In;
    wire [bit_Width -1:0] dec_Out;

    dec_gray2b #(
        .bit_width(bit_Width)
    ) DEC (.dec_out(dec_Out), .dec_in(dec_In));

    initial
    begin

        $dumpfile("dec_gray2b.vcd");
        $dumpvars(0, dec_gray2b_tb);

         $display("----------------------------------------------");    
        $display("Time(ns)\t dec_In\t dec_Out\t");
        $display("----------------------------------------------");


        dec_In = 4'b0001;
        #10;
        $display("%0t ns\t %b\t %b", $time, dec_In, dec_Out);

        dec_In = 4'b0010;
        #10;
        $display("%0t ns\t %b\t %b", $time, dec_In, dec_Out);

        dec_In = 4'b0011;
        #10;
        $display("%0t ns\t %b\t %b", $time, dec_In, dec_Out);

        dec_In = 4'b0100;
        #10;
        $display("%0t ns\t %b\t %b", $time, dec_In, dec_Out);

        dec_In = 4'b0101;
        #10;
        $display("%0t ns\t %b\t %b", $time, dec_In, dec_Out);

        dec_In = 4'b0110;
        #10;
        $display("%0t ns\t %b\t %b", $time, dec_In, dec_Out);

        dec_In = 4'b0111;
        #10;
        $display("%0t ns\t %b\t %b", $time, dec_In, dec_Out);

        dec_In = 4'b1000;
        #10;
        $display("%0t ns\t %b\t %b", $time, dec_In, dec_Out);

        $display("----------------------------------------------");
        
        $display("Simulation complete.");
        $finish;
    end

endmodule

dec_gray2b/dec_gray2b.vcd
$version Generated by VerilatedVcd $end
$timescale 1ps $end
 $scope module $rootio $end
 $upscope $end
 $scope module dec_gray2b_tb $end
  $var wire 32 % bit_Width [31:0] $end
  $var wire 4 # dec_In [3:0] $end
  $var wire 4 $ dec_Out [3:0] $end
  $scope module DEC $end
   $var wire 32 % bit_width [31:0] $end
   $var wire 4 # dec_in [3:0] $end
   $var wire 4 $ dec_out [3:0] $end
   $var wire 32 & i [31:0] $end
  $upscope $end
 $upscope $end
$enddefinitions $end


#0
b0001 #
b0001 $
b00000000000000000000000000000100 %
b11111111111111111111111111111111 &
#10000
b0010 #
b0011 $
#20000
b0011 #
b0010 $
#30000
b0100 #
b0111 $
#40000
b0101 #
b0110 $
#50000
b0110 #
b0100 $
#60000
b0111 #
b0101 $
#70000
b1000 #
b1111 $
