Register/register.v
`timescale 1 ns / 1 ps

module register #(
    parameter bit_width = 32
) (clk, rst_n, we, d_in, q_out);

    input wire clk;
    input wire rst_n;
    input wire we;
    input wire [bit_width -1:0] d_in;
    output wire [bit_width -1:0] q_out;

    reg [bit_width -1 : 0] q_reg; //internal state register (parallel D flipflops)

    assign q_out = q_reg;

    always @(posedge clk or negedge rst_n)
    begin 
        if (!rst_n)
        begin 
            q_reg <= {bit_width{1'b0}};
        end
        else
        if (we)
        begin 
            q_reg <= d_in;
        end
    end

endmodule

Register/register_tb.v
`timescale 1 ns / 1 ps

module register_tb;
    
    parameter bit_width = 32;
    reg clk;
    reg we;
    reg rst_n;
    reg [bit_width -1:0] d_in;
    wire [bit_width -1:0] q_out;

    register #(
        .bit_width(bit_width)
    ) REG (.clk(clk), .we(we), .rst_n(rst_n), .d_in(d_in), .q_out(q_out));

    always #5 clk = ~clk;

    initial
    begin 
        
        $dumpfile("register_wave.vcd");
        $dumpvars(0, register_tb);
        
        clk   = 0;
        we    = 0;
        rst_n = 0;
        d_in  = {bit_width{1'b0}};

        #12;
        rst_n = 1;

        #8;
        d_in = {bit_width{1'b1}};
        we   = 0; //q_out = 0

        #10;
        we = 1;  // q_out = d_in = {bit_width{1'b1}} = 1111111...


        #10;
        d_in = {bit_width/2{2'b10}}; // q_out = {bit_width/2{2'b10}} = 101010...;

        #10;
        we = 0;
        d_in = {bit_width/2{2'b01}}; //q_out shout not change

        #7;
        rst_n = 0; //q_out = 0000...

        #10;
        rst_n = 1;

        #20;


        $display("Test Complete");
        $finish;

    end 

endmodule

Register/register_wave.vcd
$version Generated by VerilatedVcd $end
$timescale 1ps $end
 $scope module $rootio $end
 $upscope $end
 $scope module register_tb $end
  $var wire 32 ( bit_width [31:0] $end
  $var wire 1 # clk $end
  $var wire 1 $ we $end
  $var wire 1 % rst_n $end
  $var wire 32 & d_in [31:0] $end
  $var wire 32 ' q_out [31:0] $end
  $scope module REG $end
   $var wire 32 ( bit_width [31:0] $end
   $var wire 1 # clk $end
   $var wire 1 % rst_n $end
   $var wire 1 $ we $end
   $var wire 32 & d_in [31:0] $end
   $var wire 32 ' q_out [31:0] $end
   $var wire 32 ' q_reg [31:0] $end
  $upscope $end
 $upscope $end
$enddefinitions $end


#0
0#
0$
0%
b00000000000000000000000000000000 &
b00000000000000000000000000000000 '
b00000000000000000000000000100000 (
#5000
1#
#10000
0#
#12000
1%
#15000
1#
#20000
0#
b11111111111111111111111111111111 &
#25000
1#
#30000
0#
1$
#35000
1#
b11111111111111111111111111111111 '
#40000
0#
b10101010101010101010101010101010 &
#45000
1#
b10101010101010101010101010101010 '
#50000
0#
0$
b01010101010101010101010101010101 &
#55000
1#
#57000
0%
b00000000000000000000000000000000 '
#60000
0#
#65000
1#
#67000
1%
