mux_enable/mux_enable.v
`timescale 1 ns / 1ps

module mux_enable #(
    parameter n_inputs = 16,
    parameter bit_width = 32,
    parameter n_muxS = $clog2(n_inputs)
)(mux_out, mux_in, mux_S, mux_en );

    input wire [(n_inputs * bit_width) - 1:0] mux_in;
    input wire [n_muxS - 1:0] mux_S;
    input wire mux_en;
    output reg [bit_width - 1:0] mux_out;

    always @(*)
    begin
        if (mux_en)
            begin
                mux_out = mux_in[mux_S * bit_width +: bit_width];
            end

        else
            begin
                mux_out = {bit_width{1'b0}};
            end
        
    end

endmodule

mux_enable/mux_enable_tb.v
`timescale 1ns / 1ps

module mux_enable_tb;

    parameter n_input   = 8;
    parameter bit_width = 32;
    parameter n_S       = $clog2(n_input);

    reg  [(n_input * bit_width) - 1:0] mux_in;
    reg  [n_S - 1:0]                   mux_S;
    reg                                mux_en;
    wire [bit_width - 1:0]             mux_out;

    integer i, j;
    reg [bit_width - 1:0] temp_val;

    wire [bit_width-1:0] in_wire [0:n_input-1];

    genvar g;
    generate
        for (g = 0; g < n_input; g = g + 1) begin : UNPACK_INPUTS
            assign in_wire[g] = mux_in[g * bit_width +: bit_width];
        end
    endgenerate

    mux_enable #(
        .n_inputs(n_input),
        .bit_width(bit_width)
    ) MUX (
        .mux_in(mux_in),
        .mux_S(mux_S),
        .mux_en(mux_en),
        .mux_out(mux_out)
    );

    initial 
    begin
        $dumpfile("mux_enable_wave.vcd");
        $dumpvars(0, mux_enable_tb);

        for (i = 0; i < n_input; i = i + 1) 
        begin
            temp_val = i + 1;
            mux_in[i * bit_width +: bit_width] = temp_val;
        end

        $display("========================================================================================================================");

        $write("EN\t| S\t| ");
        for (j = 0; j < n_input; j = j + 1) begin
            $write("in_%0d\t\t\t| ", j);
        end
        $display("mux_out");

        $write("--------+-------+-");
        for (j = 0; j < n_input; j = j + 1) begin
            $write("------------------------+-");
        end
        $display("----------------");

        mux_en = 1'b0;

        for (i = 0; i < n_input; i = i + 1) 
        begin
            mux_S = i[n_S-1:0];
            #10;

            $write("%0b\t| %0d\t| ", mux_en, mux_S);

            for (j = 0; j < n_input; j = j + 1) begin
                $write("0x%08h\t| ", mux_in[j * bit_width +: bit_width]);
            end

            $display("0x%08h (%0d)", mux_out, mux_out);
        end

        $write("--------+-------+-");
        for (j = 0; j < n_input; j = j + 1) begin
            $write("------------------------+-");
        end
        $display("----------------");

        mux_en = 1'b1;

        for (i = 0; i < n_input; i = i + 1) 
        begin
            mux_S = i[n_S-1:0];
            #10;

            $write("%0b\t| %0d\t| ", mux_en, mux_S);

            for (j = 0; j < n_input; j = j + 1) begin
                $write("0x%08h\t| ", mux_in[j * bit_width +: bit_width]);
            end

            $display("0x%08h (%0d)", mux_out, mux_out);
        end

        $display("========================================================================================================================\n");

        $finish;
    end

endmodule

mux_enable/mux_enable_wave.vcd
$version Generated by VerilatedVcd $end
$timescale 1ps $end
 $scope module $rootio $end
 $upscope $end
 $scope module mux_enable_tb $end
  $var wire 32 9 n_input [31:0] $end
  $var wire 32 : bit_width [31:0] $end
  $var wire 32 ; n_S [31:0] $end
  $var wire 256 # mux_in [255:0] $end
  $var wire 3 + mux_S [2:0] $end
  $var wire 1 , mux_en $end
  $var wire 32 - mux_out [31:0] $end
  $var wire 32 . i [31:0] $end
  $var wire 32 / j [31:0] $end
  $var wire 32 0 temp_val [31:0] $end
  $var wire 32 1 in_wire[0] [31:0] $end
  $var wire 32 2 in_wire[1] [31:0] $end
  $var wire 32 3 in_wire[2] [31:0] $end
  $var wire 32 4 in_wire[3] [31:0] $end
  $var wire 32 5 in_wire[4] [31:0] $end
  $var wire 32 6 in_wire[5] [31:0] $end
  $var wire 32 7 in_wire[6] [31:0] $end
  $var wire 32 8 in_wire[7] [31:0] $end
  $scope module MUX $end
   $var wire 32 9 n_inputs [31:0] $end
   $var wire 32 : bit_width [31:0] $end
   $var wire 32 ; n_muxS [31:0] $end
   $var wire 256 # mux_in [255:0] $end
   $var wire 3 + mux_S [2:0] $end
   $var wire 1 , mux_en $end
   $var wire 32 - mux_out [31:0] $end
  $upscope $end
 $upscope $end
$enddefinitions $end


#0
b0000000000000000000000000000100000000000000000000000000000000111000000000000000000000000000001100000000000000000000000000000010100000000000000000000000000000100000000000000000000000000000000110000000000000000000000000000001000000000000000000000000000000001 #
b000 +
0,
b00000000000000000000000000000000 -
b00000000000000000000000000001000 .
b00000000000000000000000000001000 /
b00000000000000000000000000001000 0
b00000000000000000000000000000001 1
b00000000000000000000000000000010 2
b00000000000000000000000000000011 3
b00000000000000000000000000000100 4
b00000000000000000000000000000101 5
b00000000000000000000000000000110 6
b00000000000000000000000000000111 7
b00000000000000000000000000001000 8
b00000000000000000000000000001000 9
b00000000000000000000000000100000 :
b00000000000000000000000000000011 ;
#10000
b001 +
b00000000000000000000000000000001 .
#20000
b010 +
b00000000000000000000000000000010 .
#30000
b011 +
b00000000000000000000000000000011 .
#40000
b100 +
b00000000000000000000000000000100 .
#50000
b101 +
b00000000000000000000000000000101 .
#60000
b110 +
b00000000000000000000000000000110 .
#70000
b111 +
b00000000000000000000000000000111 .
#80000
b000 +
1,
b00000000000000000000000000000001 -
b00000000000000000000000000001000 .
#90000
b001 +
b00000000000000000000000000000010 -
b00000000000000000000000000000001 .
#100000
b010 +
b00000000000000000000000000000011 -
b00000000000000000000000000000010 .
#110000
b011 +
b00000000000000000000000000000100 -
b00000000000000000000000000000011 .
#120000
b100 +
b00000000000000000000000000000101 -
b00000000000000000000000000000100 .
#130000
b101 +
b00000000000000000000000000000110 -
b00000000000000000000000000000101 .
#140000
b110 +
b00000000000000000000000000000111 -
b00000000000000000000000000000110 .
#150000
b111 +
b00000000000000000000000000001000 -
b00000000000000000000000000000111 .
#160000
b00000000000000000000000000001000 .
