enc_parity/enc_parity.v
`timescale 1 ns / 1ps

module enc_parity #(
    parameter n_inputs = 2,
    parameter n_outputs = $clog2(n_inputs)
    ) (enc_out, enc_in, parity);

    input wire [n_inputs - 1:0 ] enc_in;
    output reg [n_outputs - 1:0] enc_out;
    output wire parity;

    assign parity = ^enc_in;

    integer i;

    always @(*) 
    begin
        enc_out = '0;
        
        for (i = 0; i < n_inputs; i = i + 1) 
        begin
            if (enc_in[i]) 
            begin
                enc_out = i[n_outputs-1:0];
            end
        end
    end

endmodule

enc_parity/enc_parity_tb.v
`timescale 1 ns / 1 ps

module enc_parity_tb;

    parameter n_Inputs = 8;
    parameter n_Outputs = $clog2(n_Inputs);

    reg [n_Inputs - 1:0] enc_In;
    wire [n_Outputs - 1:0] enc_Out;
    wire Parity;

    enc_parity #(
        .n_inputs(n_Inputs),
        .n_outputs(n_Outputs)
    ) ENC (.enc_out(enc_Out), .enc_in(enc_In), .parity(Parity));


    initial
    begin

        $dumpfile("enc_parity_wave.vcd");
        $dumpvars(0, enc_parity_tb);


        $display("----------------------------------------------");    
        $display("Time(ns)\t enc_In\t enc_Out\t Parity");
        $display("----------------------------------------------");


        enc_In = 8'b00000001;
        #10;
        $display("%0t ns\t %b\t %b\t %b", $time, enc_In, enc_Out, Parity);

        enc_In = 8'b00000010;
        #10;
        $display("%0t ns\t %b\t %b\t %b", $time, enc_In, enc_Out, Parity);

        enc_In = 8'b00000011;
        #10;
        $display("%0t ns\t %b\t %b\t %b", $time, enc_In, enc_Out, Parity);

        enc_In = 8'b00000100;
        #10;
        $display("%0t ns\t %b\t %b\t %b", $time, enc_In, enc_Out, Parity);

        enc_In = 8'b00000101;
        #10;
        $display("%0t ns\t %b\t %b\t %b", $time, enc_In, enc_Out, Parity);

        enc_In = 8'b00000110;
        #10;
        $display("%0t ns\t %b\t %b\t %b", $time, enc_In, enc_Out, Parity);

        enc_In = 8'b00000111;
        #10;
        $display("%0t ns\t %b\t %b\t %b", $time, enc_In, enc_Out, Parity);

        enc_In = 8'b00001000;
        #10;
        $display("%0t ns\t %b\t %b\t %b", $time, enc_In, enc_Out, Parity);

        $display("----------------------------------------------");
        
        $display("Simulation complete.");
        $finish;
    end

endmodule

enc_parity/enc_parity_wave.vcd
$version Generated by VerilatedVcd $end
$timescale 1ps $end
 $scope module $rootio $end
 $upscope $end
 $scope module enc_parity_tb $end
  $var wire 32 ' n_Inputs [31:0] $end
  $var wire 32 ( n_Outputs [31:0] $end
  $var wire 8 # enc_In [7:0] $end
  $var wire 3 $ enc_Out [2:0] $end
  $var wire 1 % Parity $end
  $scope module ENC $end
   $var wire 32 ' n_inputs [31:0] $end
   $var wire 32 ( n_outputs [31:0] $end
   $var wire 8 # enc_in [7:0] $end
   $var wire 3 $ enc_out [2:0] $end
   $var wire 1 % parity $end
   $var wire 32 & i [31:0] $end
  $upscope $end
 $upscope $end
$enddefinitions $end


#0
b00000001 #
b000 $
1%
b00000000000000000000000000001000 &
b00000000000000000000000000001000 '
b00000000000000000000000000000011 (
#10000
b00000010 #
b001 $
#20000
b00000011 #
0%
#30000
b00000100 #
b010 $
1%
#40000
b00000101 #
0%
#50000
b00000110 #
#60000
b00000111 #
1%
#70000
b00001000 #
b011 $
