FIFO/fifo.v
`timescale 1 ns / 1 ps

module fifo #(
    parameter data_width = 32,
    parameter fifo_depth = 16
) (r_data, full, empty, clk, rst_n, w_en, r_en, w_data);

    input wire clk;
    input wire rst_n;
    input wire w_en;
    input wire r_en;
    input wire [data_width-1:0] w_data;
    output reg [data_width-1:0] r_data;
    output wire full;
    output wire empty;

    reg [data_width-1:0] mem [0:fifo_depth-1];
    reg [($clog2(fifo_depth))-1:0] w_ptr;
    reg [($clog2(fifo_depth))-1:0] r_ptr;
    reg [($clog2(fifo_depth)):0] count;

    assign full = (count == fifo_depth);
    assign empty = (count == 0);

    always @(posedge clk or negedge rst_n)
    begin 
        if(!rst_n)
        begin
            w_ptr <= 0;
            r_ptr <= 0;
            count <= 0;
            r_data <= 0;   

        end
        else 
        begin 
            if (w_en && !full)
            begin 
               mem[w_ptr] <= w_data;
               w_ptr <= w_ptr + 1'b1;
     
            end

            if (r_en && !empty)
            begin 
                r_data <= mem[r_ptr];
                r_ptr <= r_ptr + 1'b1;
            end

            case ({w_en && !full, r_en && !empty})
                2'b10: count <= count + 1'b1;
                2'b01: count <= count - 1'b1;

                default: count <= count;
            endcase
        end
    end

endmodule

FIFO/fifo_tb.v
`timescale 1 ns / 1 ps

module fifo_tb;

    parameter data_width = 32;
    parameter fifo_depth = 16;

    reg clk;
    reg rst_n;
    reg w_en;
    reg r_en;
    reg [data_width-1:0] w_data;
    wire [data_width-1:0] r_data;
    wire full;
    wire empty;

    
    fifo #(
        .data_width(data_width),
        .fifo_depth(fifo_depth)
    ) FIFO (
        .clk(clk),
        .rst_n(rst_n),
        .w_en(w_en),
        .r_en(r_en),
        .w_data(w_data),
        .r_data(r_data),
        .full(full),
        .empty(empty)
    );

    
    always #5 clk = ~clk;

    initial begin
        $dumpfile("fifo_wave.vcd");
        $dumpvars(0, fifo_tb);

        
        clk    = 0;
        rst_n  = 0;
        w_en   = 0;
        r_en   = 0;
        w_data = 0;

        #12 rst_n = 1; // Release reset

        // Fill the FIFO (16 Writes)
        repeat (fifo_depth) begin
            @(negedge clk);
            w_en   = 1;
            w_data = w_data + 32'h10; // Write incrementing values
        end

        // Try writing 1 extra word to check full flag protection
        @(negedge clk);
        w_data = 32'hDEADBEEF;

        @(negedge clk);
        w_en = 0;

        // Empty the FIFO (16 Reads)
        repeat (fifo_depth) begin
            @(negedge clk);
            r_en = 1;
        end

        @(negedge clk);
        r_en = 0;

        #20;
        $display("Test Complete!");
        $finish;
    end

endmodule

FIFO/fifo_wave.vcd
$version Generated by VerilatedVcd $end
$timescale 1ps $end
 $scope module $rootio $end
 $upscope $end
 $scope module fifo_tb $end
  $var wire 32 > data_width [31:0] $end
  $var wire 32 ? fifo_depth [31:0] $end
  $var wire 1 9 clk $end
  $var wire 1 : rst_n $end
  $var wire 1 ; w_en $end
  $var wire 1 < r_en $end
  $var wire 32 = w_data [31:0] $end
  $var wire 32 # r_data [31:0] $end
  $var wire 1 $ full $end
  $var wire 1 % empty $end
  $scope module FIFO $end
   $var wire 32 > data_width [31:0] $end
   $var wire 32 ? fifo_depth [31:0] $end
   $var wire 1 9 clk $end
   $var wire 1 : rst_n $end
   $var wire 1 ; w_en $end
   $var wire 1 < r_en $end
   $var wire 32 = w_data [31:0] $end
   $var wire 32 # r_data [31:0] $end
   $var wire 1 $ full $end
   $var wire 1 % empty $end
   $var wire 32 & mem[0] [31:0] $end
   $var wire 32 ' mem[1] [31:0] $end
   $var wire 32 ( mem[2] [31:0] $end
   $var wire 32 ) mem[3] [31:0] $end
   $var wire 32 * mem[4] [31:0] $end
   $var wire 32 + mem[5] [31:0] $end
   $var wire 32 , mem[6] [31:0] $end
   $var wire 32 - mem[7] [31:0] $end
   $var wire 32 . mem[8] [31:0] $end
   $var wire 32 / mem[9] [31:0] $end
   $var wire 32 0 mem[10] [31:0] $end
   $var wire 32 1 mem[11] [31:0] $end
   $var wire 32 2 mem[12] [31:0] $end
   $var wire 32 3 mem[13] [31:0] $end
   $var wire 32 4 mem[14] [31:0] $end
   $var wire 32 5 mem[15] [31:0] $end
   $var wire 4 6 w_ptr [3:0] $end
   $var wire 4 7 r_ptr [3:0] $end
   $var wire 5 8 count [4:0] $end
  $upscope $end
 $upscope $end
$enddefinitions $end


#0
b00000000000000000000000000000000 #
0$
1%
b00000000000000000000000000000000 &
b00000000000000000000000000000000 '
b00000000000000000000000000000000 (
b00000000000000000000000000000000 )
b00000000000000000000000000000000 *
b00000000000000000000000000000000 +
b00000000000000000000000000000000 ,
b00000000000000000000000000000000 -
b00000000000000000000000000000000 .
b00000000000000000000000000000000 /
b00000000000000000000000000000000 0
b00000000000000000000000000000000 1
b00000000000000000000000000000000 2
b00000000000000000000000000000000 3
b00000000000000000000000000000000 4
b00000000000000000000000000000000 5
b0000 6
b0000 7
b00000 8
09
0:
0;
0<
b00000000000000000000000000000000 =
b00000000000000000000000000100000 >
b00000000000000000000000000010000 ?
#5000
19
#10000
09
#12000
1:
#15000
19
#20000
09
1;
b00000000000000000000000000010000 =
#25000
0%
b00000000000000000000000000010000 &
b0001 6
b00001 8
19
#30000
09
b00000000000000000000000000100000 =
#35000
b00000000000000000000000000100000 '
b0010 6
b00010 8
19
#40000
09
b00000000000000000000000000110000 =
#45000
b00000000000000000000000000110000 (
b0011 6
b00011 8
19
#50000
09
b00000000000000000000000001000000 =
#55000
b00000000000000000000000001000000 )
b0100 6
b00100 8
19
#60000
09
b00000000000000000000000001010000 =
#65000
b00000000000000000000000001010000 *
b0101 6
b00101 8
19
#70000
09
b00000000000000000000000001100000 =
#75000
b00000000000000000000000001100000 +
b0110 6
b00110 8
19
#80000
09
b00000000000000000000000001110000 =
#85000
b00000000000000000000000001110000 ,
b0111 6
b00111 8
19
#90000
09
b00000000000000000000000010000000 =
#95000
b00000000000000000000000010000000 -
b1000 6
b01000 8
19
#100000
09
b00000000000000000000000010010000 =
#105000
b00000000000000000000000010010000 .
b1001 6
b01001 8
19
#110000
09
b00000000000000000000000010100000 =
#115000
b00000000000000000000000010100000 /
b1010 6
b01010 8
19
#120000
09
b00000000000000000000000010110000 =
#125000
b00000000000000000000000010110000 0
b1011 6
b01011 8
19
#130000
09
b00000000000000000000000011000000 =
#135000
b00000000000000000000000011000000 1
b1100 6
b01100 8
19
#140000
09
b00000000000000000000000011010000 =
#145000
b00000000000000000000000011010000 2
b1101 6
b01101 8
19
#150000
09
b00000000000000000000000011100000 =
#155000
b00000000000000000000000011100000 3
b1110 6
b01110 8
19
#160000
09
b00000000000000000000000011110000 =
#165000
b00000000000000000000000011110000 4
b1111 6
b01111 8
19
#170000
09
b00000000000000000000000100000000 =
#175000
1$
b00000000000000000000000100000000 5
b0000 6
b10000 8
19
#180000
09
b11011110101011011011111011101111 =
#185000
19
#190000
09
0;
#195000
19
#200000
09
1<
#205000
b00000000000000000000000000010000 #
0$
b0001 7
b01111 8
19
#210000
09
#215000
b00000000000000000000000000100000 #
b0010 7
b01110 8
19
#220000
09
#225000
b00000000000000000000000000110000 #
b0011 7
b01101 8
19
#230000
09
#235000
b00000000000000000000000001000000 #
b0100 7
b01100 8
19
#240000
09
#245000
b00000000000000000000000001010000 #
b0101 7
b01011 8
19
#250000
09
#255000
b00000000000000000000000001100000 #
b0110 7
b01010 8
19
#260000
09
#265000
b00000000000000000000000001110000 #
b0111 7
b01001 8
19
#270000
09
#275000
b00000000000000000000000010000000 #
b1000 7
b01000 8
19
#280000
09
#285000
b00000000000000000000000010010000 #
b1001 7
b00111 8
19
#290000
09
#295000
b00000000000000000000000010100000 #
b1010 7
b00110 8
19
#300000
09
#305000
b00000000000000000000000010110000 #
b1011 7
b00101 8
19
#310000
09
#315000
b00000000000000000000000011000000 #
b1100 7
b00100 8
19
#320000
09
#325000
b00000000000000000000000011010000 #
b1101 7
b00011 8
19
#330000
09
#335000
b00000000000000000000000011100000 #
b1110 7
b00010 8
19
#340000
09
#345000
b00000000000000000000000011110000 #
b1111 7
b00001 8
19
#350000
09
#355000
b00000000000000000000000100000000 #
1%
b0000 7
b00000 8
19
#360000
09
0<
