FlipFlop/Dflipflop.v
`timescale 1 ns / 1ps

module Dflipflop (q, q_bar, d, rst_n, clk);

    input wire d;
    input wire clk;
    input wire rst_n;
    output reg q;
    output wire q_bar;

    assign q_bar = ~q;

    always @(posedge clk or negedge rst_n)
    begin
        if (!rst_n)
        begin
            q <= 1'b0;
        end
        else
        begin
            q <= d;
        end

    end

endmodule

FlipFlop/Dflipflop_tb.v
`timescale 1 ns / 1 ps

module Dflipflop_tb;

    reg d;
    reg clk;
    reg rst_n;
    wire q;
    wire q_bar;

    Dflipflop FlipFlop (.q(q), .q_bar(q_bar), .d(d), .clk(clk), .rst_n(rst_n));

    always #5 clk = ~clk;

    initial
    begin 
        
        $dumpfile("Dflipflop_wave.vcd");
        $dumpvars(0, Dflipflop_tb);

        clk   = 0;
        d     = 0;
        rst_n = 0;

        #12;
        rst_n = 1;
        
        #8;
        d = 1; 
        
        #10;
        d = 0;

        #10;
        d = 1;

        #5;
        rst_n = 0;

        #10;
        rst_n = 1;

        #20;
        $display("Test Complete");
        $finish;


    end

endmodule

FlipFlop/Dflipflop_wave.vcd
$version Generated by VerilatedVcd $end
$timescale 1ps $end
 $scope module $rootio $end
 $upscope $end
 $scope module Dflipflop_tb $end
  $var wire 1 # d $end
  $var wire 1 $ clk $end
  $var wire 1 % rst_n $end
  $var wire 1 & q $end
  $var wire 1 ' q_bar $end
  $scope module FlipFlop $end
   $var wire 1 # d $end
   $var wire 1 $ clk $end
   $var wire 1 % rst_n $end
   $var wire 1 & q $end
   $var wire 1 ' q_bar $end
  $upscope $end
 $upscope $end
$enddefinitions $end


#0
0#
0$
0%
0&
1'
#5000
1$
#10000
0$
#12000
1%
#15000
1$
#20000
1#
0$
#25000
1$
1&
0'
#30000
0#
0$
#35000
1$
0&
1'
#40000
1#
0$
#45000
1$
0%
#50000
0$
#55000
1$
1%
1&
0'
