pl_cpu/program_counter.v
`timescale 1 ns / 1 ps

module program_counter #(
    parameter data_width = 32 
) (clk, rst_n, next_pc, pc, pc_plus4);

    input wire clk;
    input wire rst_n;
    input wire [data_width-1:0] next_pc;
    output reg [data_width-1:0] pc;
    output wire [data_width-1:0] pc_plus4;

    always @(posedge clk or negedge rst_n)
    begin 
        if (!rst_n)
        begin 
            pc <= {data_width{1'b0}}; 
        end
        else
        begin 
            pc <= next_pc;
        end
    end

    assign pc_plus4 = pc + 4;


endmodule

Program_Counter/program_counter_tb.v
`timescale 1 ns / 1 ps

module program_counter_tb;

    parameter data_width = 32;

    reg clk;
    reg rst_n;
    reg [data_width-1:0] next_pc;
    wire [data_width-1:0] pc;
    wire [data_width-1:0] pc_plus4;


    program_counter #(
        .data_width(data_width) 
    ) PC (.clk(clk), .rst_n(rst_n), .next_pc(next_pc), .pc(pc), .pc_plus4(pc_plus4));


    always #5 clk = ~clk;

    initial
    begin 

        $dumpfile("program_counter_wave.vcd");
        $dumpvars(0, program_counter_tb);

        clk = 0; rst_n = 0;
        next_pc = 32'h0000_0000;

        #12;
        rst_n  = 1;

        repeat (4) //sequential execution
        begin 
            @(negedge clk);
            next_pc = pc_plus4;
        end

        @(negedge clk); 
        next_pc = 32'h0000_0080; //Jump or Branch Test

        @(negedge clk);
        next_pc = pc_plus4;

        #20;
        $display("Test Complete");
        $finish;


    end

endmodule

Program_Counter/program_counter_wave.vcd
$version Generated by VerilatedVcd $end
$timescale 1ps $end
 $scope module $rootio $end
 $upscope $end
 $scope module program_counter_tb $end
  $var wire 32 ( data_width [31:0] $end
  $var wire 1 # clk $end
  $var wire 1 $ rst_n $end
  $var wire 32 % next_pc [31:0] $end
  $var wire 32 & pc [31:0] $end
  $var wire 32 ' pc_plus4 [31:0] $end
  $scope module PC $end
   $var wire 32 ( data_width [31:0] $end
   $var wire 1 # clk $end
   $var wire 1 $ rst_n $end
   $var wire 32 % next_pc [31:0] $end
   $var wire 32 & pc [31:0] $end
   $var wire 32 ' pc_plus4 [31:0] $end
  $upscope $end
 $upscope $end
$enddefinitions $end


#0
0#
0$
b00000000000000000000000000000000 %
b00000000000000000000000000000000 &
b00000000000000000000000000000100 '
b00000000000000000000000000100000 (
#5000
1#
#10000
0#
#12000
1$
#15000
1#
#20000
0#
b00000000000000000000000000000100 %
#25000
1#
b00000000000000000000000000000100 &
b00000000000000000000000000001000 '
#30000
0#
b00000000000000000000000000001000 %
#35000
1#
b00000000000000000000000000001000 &
b00000000000000000000000000001100 '
#40000
0#
b00000000000000000000000000001100 %
#45000
1#
b00000000000000000000000000001100 &
b00000000000000000000000000010000 '
#50000
0#
b00000000000000000000000000010000 %
#55000
1#
b00000000000000000000000000010000 &
b00000000000000000000000000010100 '
#60000
0#
b00000000000000000000000010000000 %
#65000
1#
b00000000000000000000000010000000 &
b00000000000000000000000010000100 '
#70000
0#
b00000000000000000000000010000100 %
#75000
1#
b00000000000000000000000010000100 &
b00000000000000000000000010001000 '
