encoder_1hot/encoder_1hot.v
`timescale 1 ns / 1ps

module encoder_1hot #(
    parameter n_inputs = 2,
    parameter n_outputs = $clog2(n_inputs)
    ) (enc_out, enc_in);

    input wire [n_inputs - 1:0 ] enc_in;
    output reg [n_outputs - 1:0] enc_out;

    integer i;

    always @(*) 
    begin
        enc_out = '0;
        
        for (i = 0; i < n_inputs; i = i + 1) 
        begin
            if (enc_in[i]) 
            begin
                enc_out = i[n_outputs-1:0];
            end
        end
    end

endmodule

encoder_1hot/encoder_1hot_tb.v
`timescale 1 ns / 1 ps

module encoder_1hot_tb;

    parameter n_Inputs = 8;
    parameter n_Outputs = $clog2(n_Inputs);

    reg [n_Inputs - 1:0] enc_In;
    wire [n_Outputs - 1:0] enc_Out;

    encoder_1hot #(
        .n_inputs(n_Inputs),
        .n_outputs(n_Outputs)
    ) ENC (.enc_out(enc_Out), .enc_in(enc_In));

    integer t;

    initial
    begin

        $dumpfile("encoder_1hot_wave.vcd");
        $dumpvars(0, encoder_1hot_tb);


        $display("----------------------------------------------");    
        $display("Time(ns)\t enc_In\t enc_Out");
        $display("----------------------------------------------");

        for (t = 0; t < n_Inputs; t = t + 1) begin
            enc_In = (1 << t);
            #10;
            
            $display("%0t ns\t\t %b\t\t %b", $time, enc_In, enc_Out);
        end

        $display("----------------------------------------------");
        
        $display("Simulation complete.");
        $finish;
    end

endmodule

encoder_1hot/encoder_1hot_wave.vcd
$version Generated by VerilatedVcd $end
$timescale 1ps $end
 $scope module $rootio $end
 $upscope $end
 $scope module encoder_1hot_tb $end
  $var wire 32 ' n_Inputs [31:0] $end
  $var wire 32 ( n_Outputs [31:0] $end
  $var wire 8 # enc_In [7:0] $end
  $var wire 3 $ enc_Out [2:0] $end
  $var wire 32 % t [31:0] $end
  $scope module ENC $end
   $var wire 32 ' n_inputs [31:0] $end
   $var wire 32 ( n_outputs [31:0] $end
   $var wire 8 # enc_in [7:0] $end
   $var wire 3 $ enc_out [2:0] $end
   $var wire 32 & i [31:0] $end
  $upscope $end
 $upscope $end
$enddefinitions $end


#0
b00000001 #
b000 $
b00000000000000000000000000000000 %
b00000000000000000000000000001000 &
b00000000000000000000000000001000 '
b00000000000000000000000000000011 (
#10000
b00000010 #
b001 $
b00000000000000000000000000000001 %
#20000
b00000100 #
b010 $
b00000000000000000000000000000010 %
#30000
b00001000 #
b011 $
b00000000000000000000000000000011 %
#40000
b00010000 #
b100 $
b00000000000000000000000000000100 %
#50000
b00100000 #
b101 $
b00000000000000000000000000000101 %
#60000
b01000000 #
b110 $
b00000000000000000000000000000110 %
#70000
b10000000 #
b111 $
b00000000000000000000000000000111 %
#80000
b00000000000000000000000000001000 %
