dec_1hot/dec_1hot.v
`timescale 1 ns / 1 ps

module dec_1hot #(
    parameter n_inputs = 4,
    parameter n_outputs = 2** (n_inputs)
) (dec_out, dec_in);

    input wire [n_inputs - 1:0] dec_in;
    output wire [n_outputs -1:0] dec_out;

    assign dec_out = 1'b1 << dec_in;


endmodule

dec_1hot/dec_1hot_tb.v
`timescale 1 ns / 1 ps

module dec_1hot_tb;

    parameter n_Inputs = 3;
    parameter n_Outputs = 2 ** (n_Inputs);

    reg [n_Inputs -1 :0] dec_In;
    wire [n_Outputs -1:0] dec_Out;

    dec_1hot #(
        .n_inputs(n_Inputs),
        .n_outputs(n_Outputs)
    ) DEC (.dec_out(dec_Out), .dec_in(dec_In));

    initial
    begin

        $dumpfile("dec_1hot_wave.vcd");
        $dumpvars(0, dec_1hot_tb);

        $display("------------------------------------------------");
        $display("Time\t dec_In\t dec_Out");
        $display("------------------------------------------------");

        dec_In = 3'b000;
        #10;
        $display("%0t ns\t %b\t %b", $time, dec_In, dec_Out);
        

        dec_In = 3'b001;
        #10;
        $display("%0t ns\t %b\t %b", $time, dec_In, dec_Out);
        

        dec_In = 3'b010;
        #10;
        $display("%0t ns\t %b\t %b", $time, dec_In, dec_Out);
        

        dec_In = 3'b011;
        #10;
        $display("%0t ns\t %b\t %b", $time, dec_In, dec_Out);
        

        dec_In = 3'b100;
        #10;
        $display("%0t ns\t %b\t %b", $time, dec_In, dec_Out);
        

        dec_In = 3'b101;
        #10;
        $display("%0t ns\t %b\t %b", $time, dec_In, dec_Out);
        

        dec_In = 3'b110;
        #10;
        $display("%0t ns\t %b\t %b", $time, dec_In, dec_Out);
        

        dec_In = 3'b111;
        #10;
        $display("%0t ns\t %b\t %b", $time, dec_In, dec_Out);
        

        $display("-------------------------------------------------");
        $display("Simulation complete");

        $finish;
    end

endmodule

dec_1hot/dec_1hot_wave.vcd
$version Generated by VerilatedVcd $end
$timescale 1ps $end
 $scope module $rootio $end
 $upscope $end
 $scope module dec_1hot_tb $end
  $var wire 32 % n_Inputs [31:0] $end
  $var wire 32 & n_Outputs [31:0] $end
  $var wire 3 # dec_In [2:0] $end
  $var wire 8 $ dec_Out [7:0] $end
  $scope module DEC $end
   $var wire 32 % n_inputs [31:0] $end
   $var wire 32 & n_outputs [31:0] $end
   $var wire 3 # dec_in [2:0] $end
   $var wire 8 $ dec_out [7:0] $end
  $upscope $end
 $upscope $end
$enddefinitions $end


#0
b000 #
b00000001 $
b00000000000000000000000000000011 %
b00000000000000000000000000001000 &
#10000
b001 #
b00000010 $
#20000
b010 #
b00000100 $
#30000
b011 #
b00001000 $
#40000
b100 #
b00010000 $
#50000
b101 #
b00100000 $
#60000
b110 #
b01000000 $
#70000
b111 #
b10000000 $
