dec_enable/dec_enable.v
`timescale 1 ns/ 1 ps

module dec_enable #(
    parameter n_inputs = 2,
    parameter n_outputs = 2 ** (n_inputs)
)(dec_out, dec_in, dec_en);

    input wire [n_inputs - 1: 0] dec_in;
    input wire dec_en;
    output reg [n_outputs -1:0] dec_out;

    always @(*)
    begin
        if (dec_en)
        begin
            dec_out = 1'b1 << dec_in;
        end
        else 
        begin
            dec_out = '0;
        end

    end

endmodule

dec_enable/dec_enable_tb.v
`timescale 1 ns / 1 ps

module dec_enable_tb;

    parameter n_Inputs = 3;
    parameter n_Outputs = 2**(n_Inputs);

    reg [n_Inputs -1:0] dec_In;
    wire [n_Outputs -1:0] dec_Out;
    reg dec_En;

    dec_enable #(
        .n_inputs(n_Inputs),
        .n_outputs(n_Outputs)
    ) DEC (.dec_out(dec_Out), .dec_in(dec_In), .dec_en(dec_En) );

    initial
    begin

          $dumpfile("dec_enable_wave.vcd");
          $dumpvars(0, dec_enable_tb);

          $display("----------------------------------------------------");
          $display("Time\t dec_In\t dec_Out\t dec_En");
          $display("----------------------------------------------------");

          dec_In = 3'b001 ; dec_En = 1'b0;
          #10;
          $display("%0t ns\t %b\t %b\t %b", $time, dec_In, dec_Out, dec_En);

          dec_In = 3'b001 ; dec_En = 1'b1;
          #10;
          $display("%0t ns\t %b\t %b\t %b", $time, dec_In, dec_Out, dec_En); 

          dec_In = 3'b011 ; dec_En = 1'b0;
          #10;
          $display("%0t ns\t %b\t %b\t %b", $time, dec_In, dec_Out, dec_En); 

          dec_In = 3'b011 ; dec_En = 1'b1;
          #10;
          $display("%0t ns\t %b\t %b\t %b", $time, dec_In, dec_Out, dec_En); 

          dec_In = 3'b100 ; dec_En = 1'b0;
          #10;
          $display("%0t ns\t %b\t %b\t %b", $time, dec_In, dec_Out, dec_En); 

          dec_In = 3'b100 ; dec_En = 1'b1;
          #10;
          $display("%0t ns\t %b\t %b\t %b", $time, dec_In, dec_Out, dec_En); 

          dec_In = 3'b101 ; dec_En = 1'b0;
          #10;
          $display("%0t ns\t %b\t %b\t %b", $time, dec_In, dec_Out, dec_En); 

          dec_In = 3'b101 ; dec_En = 1'b1;
          #10;
          $display("%0t ns\t %b\t %b\t %b", $time, dec_In, dec_Out, dec_En); 

          dec_In = 3'b111 ; dec_En = 1'b0;
          #10;
          $display("%0t ns\t %b\t %b\t %b", $time, dec_In, dec_Out, dec_En);

          dec_In = 3'b111 ; dec_En = 1'b1;
          #10;
          $display("%0t ns\t %b\t %b\t %b", $time, dec_In, dec_Out, dec_En);

          $display("---------------------------------------------------------------------");
          $display("Simulation complete");

          $finish;    
    end
endmodule

dec_enable/dec_enable_wave.vcd
$version Generated by VerilatedVcd $end
$timescale 1ps $end
 $scope module $rootio $end
 $upscope $end
 $scope module dec_enable_tb $end
  $var wire 32 & n_Inputs [31:0] $end
  $var wire 32 ' n_Outputs [31:0] $end
  $var wire 3 # dec_In [2:0] $end
  $var wire 8 $ dec_Out [7:0] $end
  $var wire 1 % dec_En $end
  $scope module DEC $end
   $var wire 32 & n_inputs [31:0] $end
   $var wire 32 ' n_outputs [31:0] $end
   $var wire 3 # dec_in [2:0] $end
   $var wire 1 % dec_en $end
   $var wire 8 $ dec_out [7:0] $end
  $upscope $end
 $upscope $end
$enddefinitions $end


#0
b001 #
b00000000 $
0%
b00000000000000000000000000000011 &
b00000000000000000000000000001000 '
#10000
b00000010 $
1%
#20000
b011 #
b00000000 $
0%
#30000
b00001000 $
1%
#40000
b100 #
b00000000 $
0%
#50000
b00010000 $
1%
#60000
b101 #
b00000000 $
0%
#70000
b00100000 $
1%
#80000
b111 #
b00000000 $
0%
#90000
b10000000 $
1%
