ALU/alu.v
`timescale 1 ns / 1 ps

module alu #(
    parameter bit_width = 8,
    parameter opcode_bits = 4
) (alu_out, alu_status, inA, inB, alu_control );

    input wire [bit_width -1 : 0] inA;
    input wire [bit_width - 1 : 0] inB;
    input wire [opcode_bits - 1 : 0] alu_control;
    output reg [bit_width - 1 : 0] alu_out;
    output reg [3:0] alu_status;

    reg Z_flag; //Zero = [0]
    reg N_flag; //Negative = [1]
    reg C_flag; //Carry = [2]
    reg V_flag; //Overflow = [3]

    reg[bit_width:0] temp;


    always @(*)
    begin
        
        temp       = {(bit_width + 1){1'b0}};
        alu_out    = {bit_width{1'b0}};
        alu_status = 4'b0000;
        C_flag = 1'b0;
        V_flag = 1'b0;
        Z_flag     = 1'b0;
        N_flag     = 1'b0;

        case (alu_control)
            
            //Add            
            4'b0000:
            begin
                    temp = {1'b0, inA} + {1'b0, inB};
                    alu_out = temp[bit_width -1:0];
                    C_flag = temp[bit_width];
                    V_flag = (inA[bit_width -1] == inB[bit_width-1]) && (alu_out[bit_width-1] != inA[bit_width -1]);

            end

            //Subtract            
            4'b0001:
            begin
                    temp = {1'b0, inA} - {1'b0, inB};
                    alu_out = temp[bit_width -1:0];
                    C_flag = ~temp[bit_width];
                    V_flag = (inA[bit_width -1] != inB[bit_width-1]) && (alu_out[bit_width-1] != inA[bit_width -1]);
            end

            //Logical Shift Left            
            4'b0010:
                    alu_out = inA << inB;

            //Logical Shift Right            
            4'b0011:
                    alu_out = inA >> inB;

            //Arithmetic Shift Left            
            4'b0100:
                    alu_out = $signed(inA) <<< inB;

            //Arithmetic Shift Right            
            4'b0101:
                    alu_out = $unsigned($signed(inA) >>> inB);

            //Circular Shift Left            
            4'b0110:
                    alu_out = (inA << inB) | (inA >> (bit_width - inB));

            //Circular Shift Right            
            4'b0111:
                    alu_out = (inA >> inB) | (inA << (bit_width - inB));

            //Logical AND            
            4'b1000:
                    alu_out = inA & inB;

            //Logical OR            
            4'b1001:
                    alu_out = inA | inB;

            //Logical XOR            
            4'b1010:
                    alu_out = inA ^ inB;

            //Logical NAND            
            4'b1011:
                    alu_out = ~(inA & inB);

            //Logical NOR            
            4'b1100:
                    alu_out = ~(inA | inB);

            //Logical XNOR            
            4'b1101:
                    alu_out = ~(inA ^ inB);

            //Equal Comparison            
            4'b1110:
                    alu_out = (inA == inB) ? {{bit_width -1{1'b0}}, 1'b1} : {bit_width{1'b0}};

            //Greater Comparison            
            4'b1111:
                    alu_out = (inA > inB) ? {{bit_width -1{1'b0}}, 1'b1} : {bit_width{1'b0}};

            default: alu_out = {bit_width{1'b0}};

        endcase

        Z_flag = (alu_out == {bit_width{1'b0}});
        N_flag = alu_out[bit_width - 1];

        alu_status = {V_flag, C_flag, N_flag, Z_flag};

    end

endmodule

ALU/alu_tb.v
`timescale 1 ns / 1 ps

module alu_tb;

    parameter bit_width   = 8;
    parameter opcode_bits = 4;

    reg  [bit_width - 1 : 0]   inA;
    reg  [bit_width - 1 : 0]   inB;
    reg  [opcode_bits - 1 : 0] alu_control;
    wire [bit_width - 1 : 0]   alu_out;
    wire [3:0]                 alu_status;

    alu #(
        .bit_width(bit_width),
        .opcode_bits(opcode_bits)
    ) uut (
        .alu_out(alu_out),
        .alu_status(alu_status),
        .inA(inA),
        .inB(inB),
        .alu_control(alu_control)
    );

    // Human-readable decimal checker task
    task check_dec(
        input signed [bit_width - 1 : 0] exp_out,
        input [3:0]                      exp_status,
        input string                     op_name
    );
        begin
            #5;
            if (alu_out !== exp_out || alu_status !== exp_status) begin
                $display("[FAIL] %-25s | A=%0d, B=%0d | Expected: Out=%0d [Status=%b] | Got: Out=%0d [Status=%b]",
                         op_name, $signed(inA), $signed(inB), exp_out, exp_status, $signed(alu_out), alu_status);
            end else begin
                $display("[PASS] %-25s | A=%0d, B=%0d => Out=%0d | Status[V C N Z]=%b", 
                         op_name, $signed(inA), $signed(inB), $signed(alu_out), alu_status);
            end
        end
    endtask

    // Hex/Binary checker task for logical operations
    task check_hex(
        input [bit_width - 1 : 0] exp_out,
        input [3:0]               exp_status,
        input string              op_name
    );
        begin
            #5;
            if (alu_out !== exp_out || alu_status !== exp_status) begin
                $display("[FAIL] %-25s | A=%b, B=%b | Expected: Out=%b [Status=%b] | Got: Out=%b [Status=%b]",
                         op_name, inA, inB, exp_out, exp_status, alu_out, alu_status);
            end else begin
                $display("[PASS] %-25s | A=%b, B=%b => Out=%b | Status[V C N Z]=%b", 
                         op_name, inA, inB, alu_out, alu_status);
            end
        end
    endtask

    initial begin
        
        $dumpfile("alu_wave.vcd");
        $dumpvars(0, alu_tb);


        $display("==================================================================================\n");

        // --- ARITHMETIC TESTS (DECIMAL DISPLAY) ---
        $display("--- 1. ADDITION TESTS ---");
        inA = 8'd10; inB = 8'd20; alu_control = 4'b0000;
        check_dec(8'd30, 4'b0000, "10 + 20");

        inA = 8'd0; inB = 8'd0; alu_control = 4'b0000;
        check_dec(8'd0, 4'b0001, "0 + 0 (Zero Flag)");

        inA = 8'd255; inB = 8'd1; alu_control = 4'b0000;
        check_dec(8'd0, 4'b0101, "255 + 1 (Unsigned Overflow)");

        inA = 8'd127; inB = 8'd1; alu_control = 4'b0000;
        check_dec(-8'd128, 4'b1010, "127 + 1 (Signed Overflow)");

        inA = -8'd128; inB = -8'd1; alu_control = 4'b0000;
        check_dec(8'd127, 4'b1100, "-128 + -1 (Signed Overflow)");


        $display("\n--- 2. SUBTRACTION TESTS ---");
        inA = 8'd30; inB = 8'd10; alu_control = 4'b0001;
        check_dec(8'd20, 4'b0000, "30 - 10");

        inA = 8'd15; inB = 8'd15; alu_control = 4'b0001;
        check_dec(8'd0, 4'b0001, "15 - 15 (Zero Flag)");

        inA = 8'd5; inB = 8'd10; alu_control = 4'b0001;
        check_dec(-8'd5, 4'b0110, "5 - 10 (Underflow/Borrow)");

        inA = 8'd127; inB = -8'd1; alu_control = 4'b0001;
        check_dec(-8'd128, 4'b1010, "127 - (-1) (Signed Overflow)");


        // --- SHIFT TESTS (DECIMAL & BINARY MIX) ---
        $display("\n--- 3. SHIFT TESTS ---");
        inA = 8'd12; inB = 8'd2; alu_control = 4'b0010;
        check_dec(8'd48, 4'b0000, "Logical Shift Left (12 << 2)");

        inA = 8'd48; inB = 8'd2; alu_control = 4'b0011;
        check_dec(8'd12, 4'b0000, "Logical Shift Right (48 >> 2)");

        inA = -8'd16; inB = 8'd2; alu_control = 4'b0101;
        check_dec(-8'd4, 4'b0010, "Arith Shift Right (-16 >>> 2)");

        inA = 8'b10000001; inB = 8'd2; alu_control = 4'b0110;
        check_hex(8'b00000110, 4'b0000, "Rotate Left");

        inA = 8'b10000001; inB = 8'd2; alu_control = 4'b0111;
        check_hex(8'b01100000, 4'b0000, "Rotate Right");


        // --- BITWISE LOGIC TESTS (BINARY DISPLAY) ---
        $display("\n--- 4. BITWISE LOGICAL TESTS ---");
        inA = 8'b11001100; inB = 8'b10101010; alu_control = 4'b1000;
        check_hex(8'b10001000, 4'b0010, "Bitwise AND");

        inA = 8'b11001100; inB = 8'b10101010; alu_control = 4'b1001;
        check_hex(8'b11101110, 4'b0010, "Bitwise OR");

        inA = 8'b11001100; inB = 8'b10101010; alu_control = 4'b1010;
        check_hex(8'b01100110, 4'b0000, "Bitwise XOR");

        inA = 8'b11001100; inB = 8'b10101010; alu_control = 4'b1011;
        check_hex(8'b01110111, 4'b0000, "Bitwise NAND");


        // --- COMPARISONS ---
        $display("\n--- 5. COMPARISON TESTS ---");
        inA = 8'd42; inB = 8'd42; alu_control = 4'b1110;
        check_dec(8'd1, 4'b0000, "Equal (42 == 42)");

        inA = 8'd42; inB = 8'd99; alu_control = 4'b1110;
        check_dec(8'd0, 4'b0001, "Equal (42 == 99)");

        inA = 8'd100; inB = 8'd50; alu_control = 4'b1111;
        check_dec(8'd1, 4'b0000, "Greater (100 > 50)");

        inA = 8'd50; inB = 8'd100; alu_control = 4'b1111;
        check_dec(8'd0, 4'b0001, "Greater (50 > 100)");

        $display("\n==================================================================================");
        $display("                            Test Complete                                ");
        $display("==================================================================================\n");
        $finish;
    end

endmodule

ALU/alu_wave.vcd
$version Generated by VerilatedVcd $end
$timescale 1ps $end
 $scope module $rootio $end
 $upscope $end
 $scope module alu_tb $end
  $var wire 32 - bit_width [31:0] $end
  $var wire 32 . opcode_bits [31:0] $end
  $var wire 8 * inA [7:0] $end
  $var wire 8 + inB [7:0] $end
  $var wire 4 , alu_control [3:0] $end
  $var wire 8 # alu_out [7:0] $end
  $var wire 4 $ alu_status [3:0] $end
  $scope module uut $end
   $var wire 32 - bit_width [31:0] $end
   $var wire 32 . opcode_bits [31:0] $end
   $var wire 8 * inA [7:0] $end
   $var wire 8 + inB [7:0] $end
   $var wire 4 , alu_control [3:0] $end
   $var wire 8 # alu_out [7:0] $end
   $var wire 4 $ alu_status [3:0] $end
   $var wire 1 % Z_flag $end
   $var wire 1 & N_flag $end
   $var wire 1 ' C_flag $end
   $var wire 1 ( V_flag $end
   $var wire 9 ) temp [8:0] $end
  $upscope $end
 $upscope $end
$enddefinitions $end


#0
b00011110 #
b0000 $
0%
0&
0'
0(
b000011110 )
b00001010 *
b00010100 +
b0000 ,
b00000000000000000000000000001000 -
b00000000000000000000000000000100 .
#5000
b00000000 #
b0001 $
1%
b000000000 )
b00000000 *
b00000000 +
#10000
b0101 $
1'
b100000000 )
b11111111 *
b00000001 +
#15000
b10000000 #
b1010 $
0%
1&
0'
1(
b010000000 )
b01111111 *
#20000
b01111111 #
b1100 $
0&
1'
b101111111 )
b10000000 *
b11111111 +
#25000
b00010100 #
b0100 $
0(
b000010100 )
b00011110 *
b00001010 +
b0001 ,
#30000
b00000000 #
b0101 $
1%
b000000000 )
b00001111 *
b00001111 +
#35000
b11111011 #
b0010 $
0%
1&
0'
b111111011 )
b00000101 *
b00001010 +
#40000
b10000000 #
b1010 $
1(
b110000000 )
b01111111 *
b11111111 +
#45000
b00110000 #
b0000 $
0&
0(
b000000000 )
b00001100 *
b00000010 +
b0010 ,
#50000
b00001100 #
b00110000 *
b0011 ,
#55000
b11111100 #
b0010 $
1&
b11110000 *
b0101 ,
#60000
b00000110 #
b0000 $
0&
b10000001 *
b0110 ,
#65000
b01100000 #
b0111 ,
#70000
b10001000 #
b0010 $
1&
b11001100 *
b10101010 +
b1000 ,
#75000
b11101110 #
b1001 ,
#80000
b01100110 #
b0000 $
0&
b1010 ,
#85000
b01110111 #
b1011 ,
#90000
b00000001 #
b00101010 *
b00101010 +
b1110 ,
#95000
b00000000 #
b0001 $
1%
b01100011 +
#100000
b00000001 #
b0000 $
0%
b01100100 *
b00110010 +
b1111 ,
#105000
b00000000 #
b0001 $
1%
b00110010 *
b01100100 +
