pl_cpu/registerFile.v
`timescale 1 ns / 1 ps

module registerFile #(
    parameter data_width = 32,
    parameter address_width = 5
)(clk, rst_n, we, w_addr, w_data, r_addr1, r_data1, r_addr2, r_data2);

    input wire clk;
    input wire rst_n;
    input wire we;
    input wire [address_width -1 :0] w_addr;
    input wire [data_width -1 :0] w_data;
    input wire [address_width -1 :0] r_addr1;
    input wire [address_width -1 :0] r_addr2;

    output wire [data_width-1 :0] r_data1;
    output wire [data_width-1 :0] r_data2;

    localparam n_regs = 2 ** (address_width);

    reg [data_width-1:0] registers [0:n_regs-1];

    integer i;

    always @(posedge clk or negedge rst_n)
    begin 
        if (!rst_n)
        begin 
            for (i = 0; i < n_regs; i=i+1)
            begin 
                registers[i] <= {data_width{1'b0}};
            end
        end
        else 
            if (we && (w_addr != 0))
            begin 
                registers[w_addr] <= w_data;
            end
    end

    assign r_data1 = (r_addr1 == 0) ? {data_width{1'b0}} : registers[r_addr1];
    assign r_data2 = (r_addr2 == 0) ? {data_width{1'b0}} : registers[r_addr2];

endmodule

Register_File/registerFile_tb.v
`timescale 1 ns / 1 ps

module registerFile_tb;

    parameter data_width = 32;
    parameter address_width = 5;

    reg clk;
    reg rst_n;
    reg we;
    reg [address_width-1:0] w_addr;
    reg [data_width-1:0] w_data;
    reg [address_width-1:0] r_addr1; 
    wire [data_width-1:0] r_data1; 
    reg [address_width-1:0] r_addr2; 
    wire [data_width-1:0] r_data2;

    registerFile #(
    .data_width(data_width),
    .address_width(address_width)
    ) RegFile (.clk(clk), .rst_n(rst_n), .we(we), .w_addr(w_addr), .w_data(w_data), .r_addr1(r_addr1), .r_data1(r_data1), .r_addr2(r_addr2), .r_data2(r_data2));

    always #5 clk = ~clk;

    initial
    begin 

        $dumpfile("regFile_wave.vcd");
        $dumpvars(0, registerFile_tb);

        clk     = 0;
        rst_n   = 0;
        we      = 0;
        w_addr  = 0;
        w_data  = {data_width{1'b0}};
        r_addr1 = 5'd1; 
        r_addr2 = 5'd2;

        #12;
        rst_n = 1; // outputs should stay 0

        #8;
        we     = 1;
        w_addr = 5'd0;
        w_data = 32'hDEAD_BEEF;

        #10;
        we     = 0;
        r_addr1 = 5'd0; // output should be 0, blocking the write

        #10;
        we     = 1;
        w_addr = 5'd1;
        w_data = 32'hAAAA_AAAA;

        #10;
        w_addr = 5'd2;
        w_data = 32'hBBBB_BBBB;

        #10;
        we      = 0; // Disable write
        r_addr1 = 5'd1; // Reads 0xAAAAAAAA
        r_addr2 = 5'd2; // Reads 0xBBBBBBBB simultaneously

        #10;
        we     = 0;
        w_addr = 5'd1;
        w_data = 32'hFFFF_FFFF; // Attempt overwrite while we=0 (should fail)

        #7;
        rst_n = 0; // Clears all registers immediately

        #10;
        rst_n = 1;

        #20;
        $display("Test complete");
        $finish;
    end

endmodule

Register_File/regFile_wave.vcd
$version Generated by VerilatedVcd $end
$timescale 1ps $end
 $scope module $rootio $end
 $upscope $end
 $scope module registerFile_tb $end
  $var wire 32 M data_width [31:0] $end
  $var wire 32 N address_width [31:0] $end
  $var wire 1 J clk $end
  $var wire 1 # rst_n $end
  $var wire 1 $ we $end
  $var wire 5 % w_addr [4:0] $end
  $var wire 32 & w_data [31:0] $end
  $var wire 5 ' r_addr1 [4:0] $end
  $var wire 32 K r_data1 [31:0] $end
  $var wire 5 ( r_addr2 [4:0] $end
  $var wire 32 L r_data2 [31:0] $end
  $scope module RegFile $end
   $var wire 32 M data_width [31:0] $end
   $var wire 32 N address_width [31:0] $end
   $var wire 1 J clk $end
   $var wire 1 # rst_n $end
   $var wire 1 $ we $end
   $var wire 5 % w_addr [4:0] $end
   $var wire 32 & w_data [31:0] $end
   $var wire 5 ' r_addr1 [4:0] $end
   $var wire 5 ( r_addr2 [4:0] $end
   $var wire 32 K r_data1 [31:0] $end
   $var wire 32 L r_data2 [31:0] $end
   $var wire 32 M n_regs [31:0] $end
   $var wire 32 ) registers[0] [31:0] $end
   $var wire 32 * registers[1] [31:0] $end
   $var wire 32 + registers[2] [31:0] $end
   $var wire 32 , registers[3] [31:0] $end
   $var wire 32 - registers[4] [31:0] $end
   $var wire 32 . registers[5] [31:0] $end
   $var wire 32 / registers[6] [31:0] $end
   $var wire 32 0 registers[7] [31:0] $end
   $var wire 32 1 registers[8] [31:0] $end
   $var wire 32 2 registers[9] [31:0] $end
   $var wire 32 3 registers[10] [31:0] $end
   $var wire 32 4 registers[11] [31:0] $end
   $var wire 32 5 registers[12] [31:0] $end
   $var wire 32 6 registers[13] [31:0] $end
   $var wire 32 7 registers[14] [31:0] $end
   $var wire 32 8 registers[15] [31:0] $end
   $var wire 32 9 registers[16] [31:0] $end
   $var wire 32 : registers[17] [31:0] $end
   $var wire 32 ; registers[18] [31:0] $end
   $var wire 32 < registers[19] [31:0] $end
   $var wire 32 = registers[20] [31:0] $end
   $var wire 32 > registers[21] [31:0] $end
   $var wire 32 ? registers[22] [31:0] $end
   $var wire 32 @ registers[23] [31:0] $end
   $var wire 32 A registers[24] [31:0] $end
   $var wire 32 B registers[25] [31:0] $end
   $var wire 32 C registers[26] [31:0] $end
   $var wire 32 D registers[27] [31:0] $end
   $var wire 32 E registers[28] [31:0] $end
   $var wire 32 F registers[29] [31:0] $end
   $var wire 32 G registers[30] [31:0] $end
   $var wire 32 H registers[31] [31:0] $end
   $var wire 32 I i [31:0] $end
  $upscope $end
 $upscope $end
$enddefinitions $end


#0
0#
0$
b00000 %
b00000000000000000000000000000000 &
b00001 '
b00010 (
b00000000000000000000000000000000 )
b00000000000000000000000000000000 *
b00000000000000000000000000000000 +
b00000000000000000000000000000000 ,
b00000000000000000000000000000000 -
b00000000000000000000000000000000 .
b00000000000000000000000000000000 /
b00000000000000000000000000000000 0
b00000000000000000000000000000000 1
b00000000000000000000000000000000 2
b00000000000000000000000000000000 3
b00000000000000000000000000000000 4
b00000000000000000000000000000000 5
b00000000000000000000000000000000 6
b00000000000000000000000000000000 7
b00000000000000000000000000000000 8
b00000000000000000000000000000000 9
b00000000000000000000000000000000 :
b00000000000000000000000000000000 ;
b00000000000000000000000000000000 <
b00000000000000000000000000000000 =
b00000000000000000000000000000000 >
b00000000000000000000000000000000 ?
b00000000000000000000000000000000 @
b00000000000000000000000000000000 A
b00000000000000000000000000000000 B
b00000000000000000000000000000000 C
b00000000000000000000000000000000 D
b00000000000000000000000000000000 E
b00000000000000000000000000000000 F
b00000000000000000000000000000000 G
b00000000000000000000000000000000 H
b00000000000000000000000000000000 I
0J
b00000000000000000000000000000000 K
b00000000000000000000000000000000 L
b00000000000000000000000000100000 M
b00000000000000000000000000000101 N
#5000
b00000000000000000000000000100000 I
1J
#10000
0J
#12000
1#
#15000
1J
#20000
1$
b11011110101011011011111011101111 &
0J
#25000
1J
#30000
0$
b00000 '
0J
#35000
1J
#40000
1$
b00001 %
b10101010101010101010101010101010 &
0J
#45000
b10101010101010101010101010101010 *
1J
#50000
b00010 %
b10111011101110111011101110111011 &
0J
#55000
b10111011101110111011101110111011 +
1J
b10111011101110111011101110111011 L
#60000
0$
b00001 '
0J
b10101010101010101010101010101010 K
#65000
1J
#70000
b00001 %
b11111111111111111111111111111111 &
0J
#75000
1J
#77000
0#
b00000000000000000000000000000000 *
b00000000000000000000000000000000 +
b00000000000000000000000000000000 K
b00000000000000000000000000000000 L
#80000
0J
#85000
1J
#87000
1#
